MANIFEST.in
README.md
setup.py
v2rayR/__init__.py
v2rayR/app.py
v2rayR/main.py
v2rayR/web.py
v2rayR.egg-info/PKG-INFO
v2rayR.egg-info/SOURCES.txt
v2rayR.egg-info/dependency_links.txt
v2rayR.egg-info/entry_points.txt
v2rayR.egg-info/not-zip-safe
v2rayR.egg-info/top_level.txt
v2rayR/config_modify/__init__.py
v2rayR/config_modify/base.py
v2rayR/config_modify/cdn.py
v2rayR/config_modify/multiple.py
v2rayR/config_modify/ss.py
v2rayR/config_modify/stream.py
v2rayR/config_modify/tls.py
v2rayR/global_setting/__init__.py
v2rayR/global_setting/ban_bt.py
v2rayR/global_setting/calcul_traffic.sh
v2rayR/global_setting/clean_iptables.sh
v2rayR/global_setting/clean_traffic.sh
v2rayR/global_setting/iptables_ctr.py
v2rayR/global_setting/stats_ctr.py
v2rayR/global_setting/update_timer.py
v2rayR/json_template/client.json
v2rayR/json_template/client_socks.json
v2rayR/json_template/client_ss.json
v2rayR/json_template/dyn_port.json
v2rayR/json_template/http.json
v2rayR/json_template/http2.json
v2rayR/json_template/kcp.json
v2rayR/json_template/mtproto.json
v2rayR/json_template/quic.json
v2rayR/json_template/server.json
v2rayR/json_template/socks.json
v2rayR/json_template/ss.json
v2rayR/json_template/stats_settings.json
v2rayR/json_template/tcp.json
v2rayR/json_template/ws.json
v2rayR/locale_i18n/en_US/LC_MESSAGES/lang.mo
v2rayR/locale_i18n/zh_CH/LC_MESSAGES/lang.mo
v2rayR/util_core/__init__.py
v2rayR/util_core/client.py
v2rayR/util_core/config.py
v2rayR/util_core/converter.py
v2rayR/util_core/group.py
v2rayR/util_core/loader.py
v2rayR/util_core/profile.py
v2rayR/util_core/selector.py
v2rayR/util_core/trans.py
v2rayR/util_core/util.cfg
v2rayR/util_core/utils.py
v2rayR/util_core/v2ray.py
v2rayR/util_core/writer.py